scatseisnet/__init__.py
scatseisnet/network.py
scatseisnet/operation.py
scatseisnet/wavelet.py
scatseisnet-0.2.1.dist-info/WHEEL
scatseisnet-0.2.1.dist-info/METADATA
scatseisnet-0.2.1.dist-info/RECORD
