Metadata-Version: 2.1
Name: scatseisnet
Version: 0.2.1
Summary: Scattering network for seismology.
Author-email: Léonard Seydoux <seydoux@ipgp.fr>, René Steinmann <rene-steinmann@web.de>, Francis Tong <francistong@gmail.com>
Requires-Python: >=3.7
Classifier: License :: OSI Approved :: GNU General Public License v3 (GPLv3)
Classifier: Programming Language :: Python :: 3
Classifier: Programming Language :: Python :: 3.7
Classifier: Programming Language :: Python :: 3.8
Classifier: Programming Language :: Python :: 3.9
Classifier: Programming Language :: Python :: 3.10
Classifier: Programming Language :: Python :: 3.11
Classifier: Intended Audience :: Developers
Classifier: Intended Audience :: Science/Research
Classifier: Topic :: Scientific/Engineering
Classifier: Operating System :: OS Independent
Requires-Dist: numpy >=1.21.6
Requires-Dist: scipy >=1.7.3
Project-URL: Documentation, https://scatseisnet.readthedocs.io/
Project-URL: Source, https://github.com/scatseisnet/scatseisnet
